pyloadlimiter/__init__.py
pyloadlimiter/composite.py
pyloadlimiter/load_limiter.py
pyloadlimiter/persistence.py
pyloadlimiter/types.py
pyloadlimiter-0.1b0.dist-info/LICENSE
pyloadlimiter-0.1b0.dist-info/METADATA
pyloadlimiter-0.1b0.dist-info/WHEEL
pyloadlimiter-0.1b0.dist-info/top_level.txt
pyloadlimiter-0.1b0.dist-info/RECORD
