Metadata-Version: 2.1
Name: pyloadlimiter
Version: 0.1b0
Summary: Python variable-sized load limiter
Home-page: https://github.com/fabiofenoglio/py-load-limiter
Author: Fabio Fenoglio
Author-email: development@fabiofenoglio.it
License: MIT
Download-URL: https://github.com/fabiofenoglio/py-load-limiter/archive/v0.1-beta.tar.gz
Keywords: LIMITER,LOAD LIMITER,RATE LIMITER
Platform: UNKNOWN
Classifier: Development Status :: 4 - Beta
Classifier: Intended Audience :: Developers
Classifier: Topic :: Software Development :: Build Tools
Classifier: License :: OSI Approved :: MIT License
Classifier: Operating System :: OS Independent
Classifier: Programming Language :: Python :: 3.6
Classifier: Programming Language :: Python :: 3.7
Classifier: Programming Language :: Python :: 3.8
Classifier: Programming Language :: Python :: 3.9
Classifier: Programming Language :: Python :: 3.10
License-File: LICENSE
